{
    "Blocks": [
        {
            "BlockType": "PAGE",
            "Geometry": {
                "BoundingBox": {
                    "Height": 1.0,
                    "Left": 0.0,
                    "Top": 0.0,
                    "Width": 1.0
                },
                "Polygon": [
                    {
                        "X": 0.0,
                        "Y": 0.0
                    },
                    {
                        "X": 0.9998493790626526,
                        "Y": 0.0
                    },
                    {
                        "X": 1.0,
                        "Y": 1.0
                    },
                    {
                        "X": 0.000496986205689609,
                        "Y": 1.0
                    }
                ]
            },
            "Id": "c8689230-e1e3-4013-8071-85a613f432e3",
            "Relationships": [
                {
                    "Ids": [
                        "0513c310-b707-4b9f-ae7b-7890a6407714",
                        "747bd7a4-7f02-49c2-b2a6-eb9122104d05",
                        "67109406-6515-4cee-9285-2827879c3708",
                        "4d283c60-e919-4e5e-a626-dead89b25fba",
                        "f537aa17-2f3a-472c-9680-82bbec7caa3c",
                        "42e36509-8ec8-41eb-83cc-d2301339c744",
                        "3b288a75-2b22-448d-970a-a7351853f40f",
                        "eb36d2f6-f92d-4032-923e-1d0397d091ca",
                        "bfa4f6da-ddc2-49df-bf81-c9ef6e5ba0b7",
                        "dbc73de2-9c98-4191-8554-49dcd80b6796",
                        "a1601003-be96-48ba-b253-541b2eced3eb",
                        "4ce3d653-3789-4f6c-befd-e7a2f088de33",
                        "d036a950-941e-4cec-afbf-d6316b29f5b4",
                        "8b79449f-dce6-4363-a365-ca0941c8cf4e",
                        "6b2348ee-d9d2-4b7a-89be-c1e1e7110ba1",
                        "deb76a05-7832-40a1-ba16-363fcb9153e0",
                        "868755fd-d6ed-47b4-986b-19cf0f2f27d5",
                        "f5542989-9fb0-44a7-95cf-6d4933d54478",
                        "542690ca-7c97-4585-88f8-1e41e677939e",
                        "21f454fb-49f7-4c9d-989b-d0d78b6ae978",
                        "d6e1ea76-f819-48e2-bfa7-9b06a02bd313",
                        "ebfe81fb-2279-4f52-a4de-edc96d10fc9e",
                        "7eac0f54-91ae-4336-acd4-8d53ff826612",
                        "1031ef34-97d8-475f-8aa1-7661e51da3f9",
                        "10c506c9-f8c1-48af-8fd0-e44d01317263",
                        "fa0b23e4-9d2e-4936-b9ea-ce9f2545186a",
                        "76b2e5eb-3852-4191-b14f-b6478d9d838e",
                        "8560a439-717e-4632-9c10-5215229e67ec",
                        "b8865e63-19ed-49f5-a491-49328740bcf3",
                        "f7c2c024-a9a3-45f5-ae33-6890f0f3e352",
                        "0d452889-7ae6-46a1-8493-3559f918b348",
                        "180c4f13-e33b-4aaf-bad8-c1425144813b",
                        "dced1da5-3992-4d08-a512-2013c623cbd3",
                        "b003e4df-d051-482e-be14-abbaf22e0d66",
                        "0de9bf12-62cf-41d4-a337-b20a42cbd8a9"
                    ],
                    "Type": "CHILD"
                }
            ]
        },
        {
            "BlockType": "LINE",
            "Confidence": 99.7417221069336,
            "Geometry": {
                "BoundingBox": {
                    "Height": 0.05415269732475281,
                    "Left": 0.027600860223174095,
                    "Top": 0.042680222541093826,
                    "Width": 0.00712780375033617
                },
                "Polygon": [
                    {
                        "X": 0.027600860223174095,
                        "Y": 0.042680222541093826
                    },
                    {
                        "X": 0.034680433571338654,
                        "Y": 0.042693547904491425
                    },
                    {
                        "X": 0.03472866490483284,
                        "Y": 0.09683292359113693
                    },
                    {
                        "X": 0.027649087831377983,
                        "Y": 0.09681953489780426
                    }
                ]
            },
            "Id": "0513c310-b707-4b9f-ae7b-7890a6407714",
            "Relationships": [
                {
                    "Ids": [
                        "af2c3905-97dc-46d0-9a50-e8e56071fe2a"
                    ],
                    "Type": "CHILD"
                }
            ],
            "Text": "1"
        },
        {
            "BlockType": "LINE",
            "Confidence": 99.94009399414062,
            "Geometry": {
                "BoundingBox": {
                    "Height": 0.046573955565690994,
                    "Left": 0.056479498744010925,
                    "Top": 0.09550037235021591,
                    "Width": 0.015506071038544178
                },
                "Polygon": [
                    {
                        "X": 0.056479498744010925,
                        "Y": 0.09550037235021591
                    },
                    {
                        "X": 0.07194410264492035,
                        "Y": 0.09552960097789764
                    },
                    {
                        "X": 0.07198557257652283,
                        "Y": 0.1420743316411972
                    },
                    {
                        "X": 0.056520964950323105,
                        "Y": 0.14204499125480652
                    }
                ]
            },
            "Id": "747bd7a4-7f02-49c2-b2a6-eb9122104d05",
            "Relationships": [
                {
                    "Ids": [
                        "0456ec7f-1ba9-40e9-a1aa-54ade4dbd71b"
                    ],
                    "Type": "CHILD"
                }
            ],
            "Text": "12"
        },
        {
            "BlockType": "LINE",
            "Confidence": 98.70698547363281,
            "Geometry": {
                "BoundingBox": {
                    "Height": 0.054029762744903564,
                    "Left": 0.07994891703128815,
                    "Top": 0.08120334148406982,
                    "Width": 0.005846263840794563
                },
                "Polygon": [
                    {
                        "X": 0.07994891703128815,
                        "Y": 0.08120334148406982
                    },
                    {
                        "X": 0.08574705570936203,
                        "Y": 0.0812142863869667
                    },
                    {
                        "X": 0.08579517900943756,
                        "Y": 0.1352331042289734
                    },
                    {
                        "X": 0.07999704778194427,
                        "Y": 0.13522212207317352
                    }
                ]
            },
            "Id": "67109406-6515-4cee-9285-2827879c3708",
            "Relationships": [
                {
                    "Ids": [
                        "d6c05e26-1e66-4e82-bffb-310955e655f6"
                    ],
                    "Type": "CHILD"
                }
            ],
            "Text": ":"
        },
        {
            "BlockType": "LINE",
            "Confidence": 99.97541046142578,
            "Geometry": {
                "BoundingBox": {
                    "Height": 0.044219691306352615,
                    "Left": 0.09359336644411087,
                    "Top": 0.0952114686369896,
                    "Width": 0.01726929470896721
                },
                "Polygon": [
                    {
                        "X": 0.09359336644411087,
                        "Y": 0.0952114686369896
                    },
                    {
                        "X": 0.11082328855991364,
                        "Y": 0.09524402767419815
                    },
                    {
                        "X": 0.11086266487836838,
                        "Y": 0.1394311487674713
                    },
                    {
                        "X": 0.09363273531198502,
                        "Y": 0.1393984854221344
                    }
                ]
            },
            "Id": "4d283c60-e919-4e5e-a626-dead89b25fba",
            "Relationships": [
                {
                    "Ids": [
                        "c098c845-8cdc-41f2-839d-101ebe28d9a8"
                    ],
                    "Type": "CHILD"
                }
            ],
            "Text": "09"
        },
        {
            "BlockType": "LINE",
            "Confidence": 99.9067611694336,
            "Geometry": {
                "BoundingBox": {
                    "Height": 0.04541422799229622,
                    "Left": 0.1385677009820938,
                    "Top": 0.0957978218793869,
                    "Width": 0.017070695757865906
                },
                "Polygon": [
                    {
                        "X": 0.1385677009820938,
                        "Y": 0.0957978218793869
                    },
                    {
                        "X": 0.15559795498847961,
                        "Y": 0.09583000838756561
                    },
                    {
                        "X": 0.15563839673995972,
                        "Y": 0.14121204614639282
                    },
                    {
                        "X": 0.1386081427335739,
                        "Y": 0.14117974042892456
                    }
                ]
            },
            "Id": "f537aa17-2f3a-472c-9680-82bbec7caa3c",
            "Relationships": [
                {
                    "Ids": [
                        "381f3e8a-3676-429d-a2ab-e7ca5fec674a"
                    ],
                    "Type": "CHILD"
                }
            ],
            "Text": "20"
        },
        {
            "BlockType": "LINE",
            "Confidence": 99.9284896850586,
            "Geometry": {
                "BoundingBox": {
                    "Height": 0.04694610461592674,
                    "Left": 0.18596623837947845,
                    "Top": 0.09512512385845184,
                    "Width": 0.01572640798985958
                },
                "Polygon": [
                    {
                        "X": 0.18596623837947845,
                        "Y": 0.09512512385845184
                    },
                    {
                        "X": 0.20165082812309265,
                        "Y": 0.0951547622680664
                    },
                    {
                        "X": 0.2016926407814026,
                        "Y": 0.14207123219966888
                    },
                    {
                        "X": 0.1860080510377884,
                        "Y": 0.14204147458076477
                    }
                ]
            },
            "Id": "42e36509-8ec8-41eb-83cc-d2301339c744",
            "Relationships": [
                {
                    "Ids": [
                        "968d9924-d66b-4cad-8866-32fc5abf1c14"
                    ],
                    "Type": "CHILD"
                }
            ],
            "Text": "12"
        },
        {
            "BlockType": "LINE",
            "Confidence": 97.8453369140625,
            "Geometry": {
                "BoundingBox": {
                    "Height": 0.051329996436834335,
                    "Left": 0.21402552723884583,
                    "Top": 0.08321312814950943,
                    "Width": 0.0051164524629712105
                },
                "Polygon": [
                    {
                        "X": 0.21402552723884583,
                        "Y": 0.08321312814950943
                    },
                    {
                        "X": 0.21909624338150024,
                        "Y": 0.08322270214557648
                    },
                    {
                        "X": 0.21914197504520416,
                        "Y": 0.13454312086105347
                    },
                    {
                        "X": 0.21407125890254974,
                        "Y": 0.13453350961208344
                    }
                ]
            },
            "Id": "3b288a75-2b22-448d-970a-a7351853f40f",
            "Relationships": [
                {
                    "Ids": [
                        "0d511c2e-c152-4c87-b043-f67d0ca700a5"
                    ],
                    "Type": "CHILD"
                }
            ],
            "Text": ":"
        },
        {
            "BlockType": "LINE",
            "Confidence": 99.94828796386719,
            "Geometry": {
                "BoundingBox": {
                    "Height": 0.04550837725400925,
                    "Left": 0.2303028255701065,
                    "Top": 0.09553854167461395,
                    "Width": 0.016938474029302597
                },
                "Polygon": [
                    {
                        "X": 0.2303028255701065,
                        "Y": 0.09553854167461395
                    },
                    {
                        "X": 0.24720075726509094,
                        "Y": 0.09557048231363297
                    },
                    {
                        "X": 0.2472412884235382,
                        "Y": 0.1410469263792038
                    },
                    {
                        "X": 0.23034335672855377,
                        "Y": 0.14101487398147583
                    }
                ]
            },
            "Id": "eb36d2f6-f92d-4032-923e-1d0397d091ca",
            "Relationships": [
                {
                    "Ids": [
                        "e533d7f7-4c2e-409b-b849-dce5ea934ab7"
                    ],
                    "Type": "CHILD"
                }
            ],
            "Text": "09"
        },
        {
            "BlockType": "LINE",
            "Confidence": 95.27284240722656,
            "Geometry": {
                "BoundingBox": {
                    "Height": 0.058565929532051086,
                    "Left": 0.2600739896297455,
                    "Top": 0.07870689779520035,
                    "Width": 0.005467582959681749
                },
                "Polygon": [
                    {
                        "X": 0.2600739896297455,
                        "Y": 0.07870689779520035
                    },
                    {
                        "X": 0.2654893696308136,
                        "Y": 0.07871711999177933
                    },
                    {
                        "X": 0.26554155349731445,
                        "Y": 0.13727281987667084
                    },
                    {
                        "X": 0.26012617349624634,
                        "Y": 0.13726255297660828
                    }
                ]
            },
            "Id": "bfa4f6da-ddc2-49df-bf81-c9ef6e5ba0b7",
            "Relationships": [
                {
                    "Ids": [
                        "738f4e1e-46fd-416e-a52a-e4fc277292a7"
                    ],
                    "Type": "CHILD"
                }
            ],
            "Text": ":"
        },
        {
            "BlockType": "LINE",
            "Confidence": 99.2329330444336,
            "Geometry": {
                "BoundingBox": {
                    "Height": 0.04473200440406799,
                    "Left": 0.2773037552833557,
                    "Top": 0.09593695402145386,
                    "Width": 0.017530526965856552
                },
                "Polygon": [
                    {
                        "X": 0.2773037552833557,
                        "Y": 0.09593695402145386
                    },
                    {
                        "X": 0.2947944402694702,
                        "Y": 0.09597001224756241
                    },
                    {
                        "X": 0.29483428597450256,
                        "Y": 0.14066895842552185
                    },
                    {
                        "X": 0.27734360098838806,
                        "Y": 0.14063578844070435
                    }
                ]
            },
            "Id": "dbc73de2-9c98-4191-8554-49dcd80b6796",
            "Relationships": [
                {
                    "Ids": [
                        "9d91cc3a-92d3-440f-b434-80f08430225e"
                    ],
                    "Type": "CHILD"
                }
            ],
            "Text": "20"
        },
        {
            "BlockType": "LINE",
            "Confidence": 99.79886627197266,
            "Geometry": {
                "BoundingBox": {
                    "Height": 0.044722624123096466,
                    "Left": 0.37313947081565857,
                    "Top": 0.09573612362146378,
                    "Width": 0.012852083891630173
                },
                "Polygon": [
                    {
                        "X": 0.37313947081565857,
                        "Y": 0.09573612362146378
                    },
                    {
                        "X": 0.3859516978263855,
                        "Y": 0.09576033800840378
                    },
                    {
                        "X": 0.38599157333374023,
                        "Y": 0.14045874774456024
                    },
                    {
                        "X": 0.3731793463230133,
                        "Y": 0.14043444395065308
                    }
                ]
            },
            "Id": "a1601003-be96-48ba-b253-541b2eced3eb",
            "Relationships": [
                {
                    "Ids": [
                        "2ad020c6-8277-479b-aec6-f91b3383085a"
                    ],
                    "Type": "CHILD"
                }
            ],
            "Text": "N"
        },
        {
            "BlockType": "LINE",
            "Confidence": 99.90121459960938,
            "Geometry": {
                "BoundingBox": {
                    "Height": 0.045112136751413345,
                    "Left": 0.43905943632125854,
                    "Top": 0.09625899791717529,
                    "Width": 0.042877599596977234
                },
                "Polygon": [
                    {
                        "X": 0.43905943632125854,
                        "Y": 0.09625899791717529
                    },
                    {
                        "X": 0.48189684748649597,
                        "Y": 0.09633995592594147
                    },
                    {
                        "X": 0.4819370210170746,
                        "Y": 0.14137113094329834
                    },
                    {
                        "X": 0.43909958004951477,
                        "Y": 0.14128988981246948
                    }
                ]
            },
            "Id": "4ce3d653-3789-4f6c-befd-e7a2f088de33",
            "Relationships": [
                {
                    "Ids": [
                        "7e90ef42-519e-4420-b8e4-40108c824fed"
                    ],
                    "Type": "CHILD"
                }
            ],
            "Text": "90834"
        },
        {
            "BlockType": "LINE",
            "Confidence": 99.63639831542969,
            "Geometry": {
                "BoundingBox": {
                    "Height": 0.045983269810676575,
                    "Left": 0.5309964418411255,
                    "Top": 0.09516692906618118,
                    "Width": 0.021088890731334686
                },
                "Polygon": [
                    {
                        "X": 0.5309964418411255,
                        "Y": 0.09516692906618118
                    },
                    {
                        "X": 0.5520443916320801,
                        "Y": 0.09520670771598816
                    },
                    {
                        "X": 0.5520853400230408,
                        "Y": 0.14115020632743835
                    },
                    {
                        "X": 0.531037449836731,
                        "Y": 0.14111028611660004
                    }
                ]
            },
            "Id": "d036a950-941e-4cec-afbf-d6316b29f5b4",
            "Relationships": [
                {
                    "Ids": [
                        "1a9b1e63-6834-402e-b160-03bd0ca99701"
                    ],
                    "Type": "CHILD"
                }
            ],
            "Text": "U6"
        },
        {
            "BlockType": "LINE",
            "Confidence": 99.92787170410156,
            "Geometry": {
                "BoundingBox": {
                    "Height": 0.046367958188056946,
                    "Left": 0.8567051291465759,
                    "Top": 0.0946974903345108,
                    "Width": 0.017559316009283066
                },
                "Polygon": [
                    {
                        "X": 0.8567051291465759,
                        "Y": 0.0946974903345108
                    },
                    {
                        "X": 0.8742230534553528,
                        "Y": 0.09473059326410294
                    },
                    {
                        "X": 0.8742644190788269,
                        "Y": 0.14106544852256775
                    },
                    {
                        "X": 0.85674649477005,
                        "Y": 0.14103223383426666
                    }
                ]
            },
            "Id": "8b79449f-dce6-4363-a365-ca0941c8cf4e",
            "Relationships": [
                {
                    "Ids": [
                        "edb0844f-66f5-4422-bd36-aa97e24b27d1"
                    ],
                    "Type": "CHILD"
                }
            ],
            "Text": "69"
        },
        {
            "BlockType": "LINE",
            "Confidence": 89.24274444580078,
            "Geometry": {
                "BoundingBox": {
                    "Height": 0.0574139766395092,
                    "Left": 0.8800302743911743,
                    "Top": 0.07945861667394638,
                    "Width": 0.005935013759881258
                },
                "Polygon": [
                    {
                        "X": 0.8800302743911743,
                        "Y": 0.07945861667394638
                    },
                    {
                        "X": 0.8859140276908875,
                        "Y": 0.0794697180390358
                    },
                    {
                        "X": 0.8859652876853943,
                        "Y": 0.13687258958816528
                    },
                    {
                        "X": 0.8800815343856812,
                        "Y": 0.13686144351959229
                    }
                ]
            },
            "Id": "6b2348ee-d9d2-4b7a-89be-c1e1e7110ba1",
            "Relationships": [
                {
                    "Ids": [
                        "2415d33e-afe1-4ea2-a774-beac1001dece"
                    ],
                    "Type": "CHILD"
                }
            ],
            "Text": ":"
        },
        {
            "BlockType": "LINE",
            "Confidence": 99.85006713867188,
            "Geometry": {
                "BoundingBox": {
                    "Height": 0.04500124230980873,
                    "Left": 0.8979013562202454,
                    "Top": 0.09533959627151489,
                    "Width": 0.017771238461136818
                },
                "Polygon": [
                    {
                        "X": 0.8979013562202454,
                        "Y": 0.09533959627151489
                    },
                    {
                        "X": 0.915632426738739,
                        "Y": 0.09537310153245926
                    },
                    {
                        "X": 0.9156725406646729,
                        "Y": 0.14034083485603333
                    },
                    {
                        "X": 0.8979414701461792,
                        "Y": 0.1403072029352188
                    }
                ]
            },
            "Id": "deb76a05-7832-40a1-ba16-363fcb9153e0",
            "Relationships": [
                {
                    "Ids": [
                        "e06d501a-a8ef-4079-a639-5edb87048f34"
                    ],
                    "Type": "CHILD"
                }
            ],
            "Text": "74"
        },
        {
            "BlockType": "LINE",
            "Confidence": 97.15982818603516,
            "Geometry": {
                "BoundingBox": {
                    "Height": 0.04500617831945419,
                    "Left": 0.9329209327697754,
                    "Top": 0.09589587152004242,
                    "Width": 0.028548410162329674
                },
                "Polygon": [
                    {
                        "X": 0.9329209327697754,
                        "Y": 0.09589587152004242
                    },
                    {
                        "X": 0.9614291787147522,
                        "Y": 0.09594974666833878
                    },
                    {
                        "X": 0.9614693522453308,
                        "Y": 0.1409020572900772
                    },
                    {
                        "X": 0.9329610466957092,
                        "Y": 0.14084798097610474
                    }
                ]
            },
            "Id": "868755fd-d6ed-47b4-986b-19cf0f2f27d5",
            "Relationships": [
                {
                    "Ids": [
                        "7c5296dd-40eb-47f1-97bc-0c131f0a98d2"
                    ],
                    "Type": "CHILD"
                }
            ],
            "Text": "1.00"
        },
        {
            "BlockType": "LINE",
            "Confidence": 99.79341888427734,
            "Geometry": {
                "BoundingBox": {
                    "Height": 0.05610784888267517,
                    "Left": 0.02595418319106102,
                    "Top": 0.2168072909116745,
                    "Width": 0.011259674094617367
                },
                "Polygon": [
                    {
                        "X": 0.02595418319106102,
                        "Y": 0.2168072909116745
                    },
                    {
                        "X": 0.03716389462351799,
                        "Y": 0.21682867407798767
                    },
                    {
                        "X": 0.03721385821700096,
                        "Y": 0.27291515469551086
                    },
                    {
                        "X": 0.026004144921898842,
                        "Y": 0.27289366722106934
                    }
                ]
            },
            "Id": "f5542989-9fb0-44a7-95cf-6d4933d54478",
            "Relationships": [
                {
                    "Ids": [
                        "10c201b5-eb7b-453f-a671-4b4b1fb9e5a5"
                    ],
                    "Type": "CHILD"
                }
            ],
            "Text": "2"
        },
        {
            "BlockType": "LINE",
            "Confidence": 99.85658264160156,
            "Geometry": {
                "BoundingBox": {
                    "Height": 0.04529564455151558,
                    "Left": 0.05626837909221649,
                    "Top": 0.2657124102115631,
                    "Width": 0.015989314764738083
                },
                "Polygon": [
                    {
                        "X": 0.05626837909221649,
                        "Y": 0.2657124102115631
                    },
                    {
                        "X": 0.07221736758947372,
                        "Y": 0.2657429575920105
                    },
                    {
                        "X": 0.07225769013166428,
                        "Y": 0.3110080659389496
                    },
                    {
                        "X": 0.05630870535969734,
                        "Y": 0.31097739934921265
                    }
                ]
            },
            "Id": "542690ca-7c97-4585-88f8-1e41e677939e",
            "Relationships": [
                {
                    "Ids": [
                        "e4a99ceb-8907-4366-ac97-4a7a045ada7c"
                    ],
                    "Type": "CHILD"
                }
            ],
            "Text": "12"
        },
        {
            "BlockType": "LINE",
            "Confidence": 99.95601654052734,
            "Geometry": {
                "BoundingBox": {
                    "Height": 0.04562271013855934,
                    "Left": 0.09267235547304153,
                    "Top": 0.26535433530807495,
                    "Width": 0.017770078033208847
                },
                "Polygon": [
                    {
                        "X": 0.09267235547304153,
                        "Y": 0.26535433530807495
                    },
                    {
                        "X": 0.11040181666612625,
                        "Y": 0.26538828015327454
                    },
                    {
                        "X": 0.11044243723154068,
                        "Y": 0.310977041721344
                    },
                    {
                        "X": 0.09271297603845596,
                        "Y": 0.31094297766685486
                    }
                ]
            },
            "Id": "21f454fb-49f7-4c9d-989b-d0d78b6ae978",
            "Relationships": [
                {
                    "Ids": [
                        "f9895571-9d24-4417-a46c-5070cc78f516"
                    ],
                    "Type": "CHILD"
                }
            ],
            "Text": "09"
        },
        {
            "BlockType": "LINE",
            "Confidence": 99.89064025878906,
            "Geometry": {
                "BoundingBox": {
                    "Height": 0.045544568449258804,
                    "Left": 0.1385493129491806,
                    "Top": 0.26516157388687134,
                    "Width": 0.017374582588672638
                },
                "Polygon": [
                    {
                        "X": 0.1385493129491806,
                        "Y": 0.26516157388687134
                    },
                    {
                        "X": 0.15588334202766418,
                        "Y": 0.26519477367401123
                    },
                    {
                        "X": 0.15592388808727264,
                        "Y": 0.31070616841316223
                    },
                    {
                        "X": 0.13858987390995026,
                        "Y": 0.3106728494167328
                    }
                ]
            },
            "Id": "d6e1ea76-f819-48e2-bfa7-9b06a02bd313",
            "Relationships": [
                {
                    "Ids": [
                        "dc4cd42e-6475-42d2-a1a8-b2bc68eb9476"
                    ],
                    "Type": "CHILD"
                }
            ],
            "Text": "20"
        },
        {
            "BlockType": "LINE",
            "Confidence": 99.69669342041016,
            "Geometry": {
                "BoundingBox": {
                    "Height": 0.045257873833179474,
                    "Left": 0.18564236164093018,
                    "Top": 0.2654660642147064,
                    "Width": 0.01642664708197117
                },
                "Polygon": [
                    {
                        "X": 0.18564236164093018,
                        "Y": 0.2654660642147064
                    },
                    {
                        "X": 0.20202870666980743,
                        "Y": 0.26549744606018066
                    },
                    {
                        "X": 0.2020690143108368,
                        "Y": 0.3107239603996277
                    },
                    {
                        "X": 0.18568266928195953,
                        "Y": 0.3106924593448639
                    }
                ]
            },
            "Id": "ebfe81fb-2279-4f52-a4de-edc96d10fc9e",
            "Relationships": [
                {
                    "Ids": [
                        "42ca010b-225e-484e-aa1e-cde0a53526b5"
                    ],
                    "Type": "CHILD"
                }
            ],
            "Text": "12"
        },
        {
            "BlockType": "LINE",
            "Confidence": 99.3494873046875,
            "Geometry": {
                "BoundingBox": {
                    "Height": 0.04485385864973068,
                    "Left": 0.22903896868228912,
                    "Top": 0.2658660411834717,
                    "Width": 0.018566258251667023
                },
                "Polygon": [
                    {
                        "X": 0.22903896868228912,
                        "Y": 0.2658660411834717
                    },
                    {
                        "X": 0.24756528437137604,
                        "Y": 0.26590150594711304
                    },
                    {
                        "X": 0.24760523438453674,
                        "Y": 0.31071987748146057
                    },
                    {
                        "X": 0.22907891869544983,
                        "Y": 0.31068429350852966
                    }
                ]
            },
            "Id": "7eac0f54-91ae-4336-acd4-8d53ff826612",
            "Relationships": [
                {
                    "Ids": [
                        "c385671c-0a1c-432d-a98c-f9be02b065df"
                    ],
                    "Type": "CHILD"
                }
            ],
            "Text": "09"
        },
        {
            "BlockType": "LINE",
            "Confidence": 99.02058410644531,
            "Geometry": {
                "BoundingBox": {
                    "Height": 0.04509974271059036,
                    "Left": 0.2769503891468048,
                    "Top": 0.2657829523086548,
                    "Width": 0.01728205941617489
                },
                "Polygon": [
                    {
                        "X": 0.2769503891468048,
                        "Y": 0.2657829523086548
                    },
                    {
                        "X": 0.29419228434562683,
                        "Y": 0.26581597328186035
                    },
                    {
                        "X": 0.29423245787620544,
                        "Y": 0.31088268756866455
                    },
                    {
                        "X": 0.2769905626773834,
                        "Y": 0.31084954738616943
                    }
                ]
            },
            "Id": "1031ef34-97d8-475f-8aa1-7661e51da3f9",
            "Relationships": [
                {
                    "Ids": [
                        "3b0b992a-6c44-4923-9eb6-7d1c2ebfe8d0"
                    ],
                    "Type": "CHILD"
                }
            ],
            "Text": "20"
        },
        {
            "BlockType": "LINE",
            "Confidence": 93.3573989868164,
            "Geometry": {
                "BoundingBox": {
                    "Height": 0.044209521263837814,
                    "Left": 0.3242138624191284,
                    "Top": 0.26611897349357605,
                    "Width": 0.014980372041463852
                },
                "Polygon": [
                    {
                        "X": 0.3242138624191284,
                        "Y": 0.26611897349357605
                    },
                    {
                        "X": 0.33915483951568604,
                        "Y": 0.26614758372306824
                    },
                    {
                        "X": 0.33919423818588257,
                        "Y": 0.31032848358154297
                    },
                    {
                        "X": 0.32425326108932495,
                        "Y": 0.3102997839450836
                    }
                ]
            },
            "Id": "10c506c9-f8c1-48af-8fd0-e44d01317263",
            "Relationships": [
                {
                    "Ids": [
                        "88c9a6ba-4ec2-4cd7-ab66-2ce7eca37fa8"
                    ],
                    "Type": "CHILD"
                }
            ],
            "Text": "11"
        },
        {
            "BlockType": "LINE",
            "Confidence": 99.90327453613281,
            "Geometry": {
                "BoundingBox": {
                    "Height": 0.045588213950395584,
                    "Left": 0.3731483221054077,
                    "Top": 0.26455411314964294,
                    "Width": 0.012919125147163868
                },
                "Polygon": [
                    {
                        "X": 0.3731483221054077,
                        "Y": 0.26455411314964294
                    },
                    {
                        "X": 0.3860268294811249,
                        "Y": 0.26457878947257996
                    },
                    {
                        "X": 0.3860674500465393,
                        "Y": 0.3101423382759094
                    },
                    {
                        "X": 0.37318894267082214,
                        "Y": 0.31011760234832764
                    }
                ]
            },
            "Id": "fa0b23e4-9d2e-4936-b9ea-ce9f2545186a",
            "Relationships": [
                {
                    "Ids": [
                        "76bb1556-e1ba-4e5d-a9f9-94902a065326"
                    ],
                    "Type": "CHILD"
                }
            ],
            "Text": "N"
        },
        {
            "BlockType": "LINE",
            "Confidence": 88.85499572753906,
            "Geometry": {
                "BoundingBox": {
                    "Height": 0.047276221215724945,
                    "Left": 0.4362429678440094,
                    "Top": 0.2644710838794708,
                    "Width": 0.04769366979598999
                },
                "Polygon": [
                    {
                        "X": 0.4362429678440094,
                        "Y": 0.2644710838794708
                    },
                    {
                        "X": 0.48389455676078796,
                        "Y": 0.26456233859062195
                    },
                    {
                        "X": 0.4839366376399994,
                        "Y": 0.31174731254577637
                    },
                    {
                        "X": 0.4362850487232208,
                        "Y": 0.311655730009079
                    }
                ]
            },
            "Id": "76b2e5eb-3852-4191-b14f-b6478d9d838e",
            "Relationships": [
                {
                    "Ids": [
                        "d1099fb1-fbee-42fa-9090-8a9c5fa162b8"
                    ],
                    "Type": "CHILD"
                }
            ],
            "Text": "110048"
        },
        {
            "BlockType": "LINE",
            "Confidence": 90.33728790283203,
            "Geometry": {
                "BoundingBox": {
                    "Height": 0.047508589923381805,
                    "Left": 0.7154537439346313,
                    "Top": 0.2642938196659088,
                    "Width": 0.007012603338807821
                },
                "Polygon": [
                    {
                        "X": 0.7154537439346313,
                        "Y": 0.2642938196659088
                    },
                    {
                        "X": 0.7224239706993103,
                        "Y": 0.2643071711063385
                    },
                    {
                        "X": 0.7224663496017456,
                        "Y": 0.3118024170398712
                    },
                    {
                        "X": 0.7154961228370667,
                        "Y": 0.31178900599479675
                    }
                ]
            },
            "Id": "8560a439-717e-4632-9c10-5215229e67ec",
            "Relationships": [
                {
                    "Ids": [
                        "6d9386ca-c1d1-462e-b87c-8a5d8e5a095d"
                    ],
                    "Type": "CHILD"
                }
            ],
            "Text": "1"
        },
        {
            "BlockType": "LINE",
            "Confidence": 99.91776275634766,
            "Geometry": {
                "BoundingBox": {
                    "Height": 0.04535893723368645,
                    "Left": 0.8582285046577454,
                    "Top": 0.2653377652168274,
                    "Width": 0.016538573428988457
                },
                "Polygon": [
                    {
                        "X": 0.8582285046577454,
                        "Y": 0.2653377652168274
                    },
                    {
                        "X": 0.8747265934944153,
                        "Y": 0.26536935567855835
                    },
                    {
                        "X": 0.8747670650482178,
                        "Y": 0.31069669127464294
                    },
                    {
                        "X": 0.8582689762115479,
                        "Y": 0.3106650114059448
                    }
                ]
            },
            "Id": "b8865e63-19ed-49f5-a491-49328740bcf3",
            "Relationships": [
                {
                    "Ids": [
                        "b33b1831-d3ff-43b7-9c47-9cb1a558f87e"
                    ],
                    "Type": "CHILD"
                }
            ],
            "Text": "14"
        },
        {
            "BlockType": "LINE",
            "Confidence": 99.79928588867188,
            "Geometry": {
                "BoundingBox": {
                    "Height": 0.04683927819132805,
                    "Left": 0.8980045318603516,
                    "Top": 0.2645419239997864,
                    "Width": 0.017436541616916656
                },
                "Polygon": [
                    {
                        "X": 0.8980045318603516,
                        "Y": 0.2645419239997864
                    },
                    {
                        "X": 0.9153993129730225,
                        "Y": 0.2645752429962158
                    },
                    {
                        "X": 0.91544109582901,
                        "Y": 0.31138119101524353
                    },
                    {
                        "X": 0.8980463147163391,
                        "Y": 0.3113477826118469
                    }
                ]
            },
            "Id": "f7c2c024-a9a3-45f5-ae33-6890f0f3e352",
            "Relationships": [
                {
                    "Ids": [
                        "de93b898-7960-4a35-9348-f475c0b02e20"
                    ],
                    "Type": "CHILD"
                }
            ],
            "Text": "48"
        },
        {
            "BlockType": "LINE",
            "Confidence": 99.82959747314453,
            "Geometry": {
                "BoundingBox": {
                    "Height": 0.04632692039012909,
                    "Left": 0.932571291923523,
                    "Top": 0.26500779390335083,
                    "Width": 0.028995519503951073
                },
                "Polygon": [
                    {
                        "X": 0.932571291923523,
                        "Y": 0.26500779390335083
                    },
                    {
                        "X": 0.9615254998207092,
                        "Y": 0.26506322622299194
                    },
                    {
                        "X": 0.9615668654441833,
                        "Y": 0.3113346993923187
                    },
                    {
                        "X": 0.9326126575469971,
                        "Y": 0.3112790584564209
                    }
                ]
            },
            "Id": "0d452889-7ae6-46a1-8493-3559f918b348",
            "Relationships": [
                {
                    "Ids": [
                        "7c62a70f-a3e4-4a65-92c8-7e86e1042545"
                    ],
                    "Type": "CHILD"
                }
            ],
            "Text": "1.00"
        },
        {
            "BlockType": "LINE",
            "Confidence": 99.4665756225586,
            "Geometry": {
                "BoundingBox": {
                    "Height": 0.06432473659515381,
                    "Left": 0.02487802878022194,
                    "Top": 0.3840811848640442,
                    "Width": 0.011113501153886318
                },
                "Polygon": [
                    {
                        "X": 0.02487802878022194,
                        "Y": 0.3840811848640442
                    },
                    {
                        "X": 0.03593424707651138,
                        "Y": 0.38410255312919617
                    },
                    {
                        "X": 0.03599153086543083,
                        "Y": 0.448405921459198
                    },
                    {
                        "X": 0.02493531070649624,
                        "Y": 0.44838446378707886
                    }
                ]
            },
            "Id": "180c4f13-e33b-4aaf-bad8-c1425144813b",
            "Relationships": [
                {
                    "Ids": [
                        "95e4d7fc-056c-42ac-abda-f00dcf1023f0"
                    ],
                    "Type": "CHILD"
                }
            ],
            "Text": "3"
        },
        {
            "BlockType": "LINE",
            "Confidence": 99.91659545898438,
            "Geometry": {
                "BoundingBox": {
                    "Height": 0.056307971477508545,
                    "Left": 0.026298193261027336,
                    "Top": 0.5553244352340698,
                    "Width": 0.011234186589717865
                },
                "Polygon": [
                    {
                        "X": 0.026298193261027336,
                        "Y": 0.5553244352340698
                    },
                    {
                        "X": 0.03748223930597305,
                        "Y": 0.5553463101387024
                    },
                    {
                        "X": 0.03753238171339035,
                        "Y": 0.6116324067115784
                    },
                    {
                        "X": 0.026348333805799484,
                        "Y": 0.6116104125976562
                    }
                ]
            },
            "Id": "dced1da5-3992-4d08-a512-2013c623cbd3",
            "Relationships": [
                {
                    "Ids": [
                        "8b27c573-f4f5-4ece-8e2f-01124d6262d3"
                    ],
                    "Type": "CHILD"
                }
            ],
            "Text": "4"
        },
        {
            "BlockType": "LINE",
            "Confidence": 99.08972930908203,
            "Geometry": {
                "BoundingBox": {
                    "Height": 0.05685964971780777,
                    "Left": 0.026742946356534958,
                    "Top": 0.7319079637527466,
                    "Width": 0.010450838133692741
                },
                "Polygon": [
                    {
                        "X": 0.026742946356534958,
                        "Y": 0.7319079637527466
                    },
                    {
                        "X": 0.037143148481845856,
                        "Y": 0.7319285869598389
                    },
                    {
                        "X": 0.03719378262758255,
                        "Y": 0.7887676358222961
                    },
                    {
                        "X": 0.026793578639626503,
                        "Y": 0.7887468934059143
                    }
                ]
            },
            "Id": "b003e4df-d051-482e-be14-abbaf22e0d66",
            "Relationships": [
                {
                    "Ids": [
                        "3518a893-2198-44e0-8561-6964f3695b34"
                    ],
                    "Type": "CHILD"
                }
            ],
            "Text": "5"
        },
        {
            "BlockType": "LINE",
            "Confidence": 99.87584686279297,
            "Geometry": {
                "BoundingBox": {
                    "Height": 0.05692388117313385,
                    "Left": 0.026133118197321892,
                    "Top": 0.9041671752929688,
                    "Width": 0.011987566947937012
                },
                "Polygon": [
                    {
                        "X": 0.026133118197321892,
                        "Y": 0.9041671752929688
                    },
                    {
                        "X": 0.03806999698281288,
                        "Y": 0.9041911363601685
                    },
                    {
                        "X": 0.038120683282613754,
                        "Y": 0.9610910415649414
                    },
                    {
                        "X": 0.026183804497122765,
                        "Y": 0.9610669612884521
                    }
                ]
            },
            "Id": "0de9bf12-62cf-41d4-a337-b20a42cbd8a9",
            "Relationships": [
                {
                    "Ids": [
                        "635a593f-c70f-4e0b-a888-51ad8f20aade"
                    ],
                    "Type": "CHILD"
                }
            ],
            "Text": "6"
        },
        {
            "BlockType": "WORD",
            "Confidence": 99.7417221069336,
            "Geometry": {
                "BoundingBox": {
                    "Height": 0.05415269732475281,
                    "Left": 0.027600860223174095,
                    "Top": 0.042680222541093826,
                    "Width": 0.00712780375033617
                },
                "Polygon": [
                    {
                        "X": 0.027600860223174095,
                        "Y": 0.042680222541093826
                    },
                    {
                        "X": 0.034680433571338654,
                        "Y": 0.042693547904491425
                    },
                    {
                        "X": 0.03472866490483284,
                        "Y": 0.09683292359113693
                    },
                    {
                        "X": 0.027649087831377983,
                        "Y": 0.09681953489780426
                    }
                ]
            },
            "Id": "af2c3905-97dc-46d0-9a50-e8e56071fe2a",
            "Text": "1",
            "TextType": "PRINTED"
        },
        {
            "BlockType": "WORD",
            "Confidence": 99.94009399414062,
            "Geometry": {
                "BoundingBox": {
                    "Height": 0.046573955565690994,
                    "Left": 0.056479498744010925,
                    "Top": 0.09550037235021591,
                    "Width": 0.015506071038544178
                },
                "Polygon": [
                    {
                        "X": 0.056479498744010925,
                        "Y": 0.09550037235021591
                    },
                    {
                        "X": 0.07194410264492035,
                        "Y": 0.09552960097789764
                    },
                    {
                        "X": 0.07198557257652283,
                        "Y": 0.1420743316411972
                    },
                    {
                        "X": 0.056520964950323105,
                        "Y": 0.14204499125480652
                    }
                ]
            },
            "Id": "0456ec7f-1ba9-40e9-a1aa-54ade4dbd71b",
            "Text": "12",
            "TextType": "PRINTED"
        },
        {
            "BlockType": "WORD",
            "Confidence": 98.70698547363281,
            "Geometry": {
                "BoundingBox": {
                    "Height": 0.054029762744903564,
                    "Left": 0.07994891703128815,
                    "Top": 0.08120334148406982,
                    "Width": 0.005846263840794563
                },
                "Polygon": [
                    {
                        "X": 0.07994891703128815,
                        "Y": 0.08120334148406982
                    },
                    {
                        "X": 0.08574705570936203,
                        "Y": 0.0812142863869667
                    },
                    {
                        "X": 0.08579517900943756,
                        "Y": 0.1352331042289734
                    },
                    {
                        "X": 0.07999704778194427,
                        "Y": 0.13522212207317352
                    }
                ]
            },
            "Id": "d6c05e26-1e66-4e82-bffb-310955e655f6",
            "Text": ":",
            "TextType": "PRINTED"
        },
        {
            "BlockType": "WORD",
            "Confidence": 99.97541046142578,
            "Geometry": {
                "BoundingBox": {
                    "Height": 0.044219691306352615,
                    "Left": 0.09359336644411087,
                    "Top": 0.0952114686369896,
                    "Width": 0.01726929470896721
                },
                "Polygon": [
                    {
                        "X": 0.09359336644411087,
                        "Y": 0.0952114686369896
                    },
                    {
                        "X": 0.11082328855991364,
                        "Y": 0.09524402767419815
                    },
                    {
                        "X": 0.11086266487836838,
                        "Y": 0.1394311487674713
                    },
                    {
                        "X": 0.09363273531198502,
                        "Y": 0.1393984854221344
                    }
                ]
            },
            "Id": "c098c845-8cdc-41f2-839d-101ebe28d9a8",
            "Text": "09",
            "TextType": "PRINTED"
        },
        {
            "BlockType": "WORD",
            "Confidence": 99.9067611694336,
            "Geometry": {
                "BoundingBox": {
                    "Height": 0.04541422799229622,
                    "Left": 0.1385677009820938,
                    "Top": 0.0957978218793869,
                    "Width": 0.017070695757865906
                },
                "Polygon": [
                    {
                        "X": 0.1385677009820938,
                        "Y": 0.0957978218793869
                    },
                    {
                        "X": 0.15559795498847961,
                        "Y": 0.09583000838756561
                    },
                    {
                        "X": 0.15563839673995972,
                        "Y": 0.14121204614639282
                    },
                    {
                        "X": 0.1386081427335739,
                        "Y": 0.14117974042892456
                    }
                ]
            },
            "Id": "381f3e8a-3676-429d-a2ab-e7ca5fec674a",
            "Text": "20",
            "TextType": "PRINTED"
        },
        {
            "BlockType": "WORD",
            "Confidence": 99.9284896850586,
            "Geometry": {
                "BoundingBox": {
                    "Height": 0.04694610461592674,
                    "Left": 0.18596623837947845,
                    "Top": 0.09512512385845184,
                    "Width": 0.01572640798985958
                },
                "Polygon": [
                    {
                        "X": 0.18596623837947845,
                        "Y": 0.09512512385845184
                    },
                    {
                        "X": 0.20165082812309265,
                        "Y": 0.0951547622680664
                    },
                    {
                        "X": 0.2016926407814026,
                        "Y": 0.14207123219966888
                    },
                    {
                        "X": 0.1860080510377884,
                        "Y": 0.14204147458076477
                    }
                ]
            },
            "Id": "968d9924-d66b-4cad-8866-32fc5abf1c14",
            "Text": "12",
            "TextType": "PRINTED"
        },
        {
            "BlockType": "WORD",
            "Confidence": 97.8453369140625,
            "Geometry": {
                "BoundingBox": {
                    "Height": 0.051329996436834335,
                    "Left": 0.21402552723884583,
                    "Top": 0.08321312814950943,
                    "Width": 0.0051164524629712105
                },
                "Polygon": [
                    {
                        "X": 0.21402552723884583,
                        "Y": 0.08321312814950943
                    },
                    {
                        "X": 0.21909624338150024,
                        "Y": 0.08322270214557648
                    },
                    {
                        "X": 0.21914197504520416,
                        "Y": 0.13454312086105347
                    },
                    {
                        "X": 0.21407125890254974,
                        "Y": 0.13453350961208344
                    }
                ]
            },
            "Id": "0d511c2e-c152-4c87-b043-f67d0ca700a5",
            "Text": ":",
            "TextType": "PRINTED"
        },
        {
            "BlockType": "WORD",
            "Confidence": 99.94828796386719,
            "Geometry": {
                "BoundingBox": {
                    "Height": 0.04550837725400925,
                    "Left": 0.2303028255701065,
                    "Top": 0.09553854167461395,
                    "Width": 0.016938474029302597
                },
                "Polygon": [
                    {
                        "X": 0.2303028255701065,
                        "Y": 0.09553854167461395
                    },
                    {
                        "X": 0.24720075726509094,
                        "Y": 0.09557048231363297
                    },
                    {
                        "X": 0.2472412884235382,
                        "Y": 0.1410469263792038
                    },
                    {
                        "X": 0.23034335672855377,
                        "Y": 0.14101487398147583
                    }
                ]
            },
            "Id": "e533d7f7-4c2e-409b-b849-dce5ea934ab7",
            "Text": "09",
            "TextType": "PRINTED"
        },
        {
            "BlockType": "WORD",
            "Confidence": 95.27284240722656,
            "Geometry": {
                "BoundingBox": {
                    "Height": 0.058565929532051086,
                    "Left": 0.2600739896297455,
                    "Top": 0.07870689779520035,
                    "Width": 0.005467582959681749
                },
                "Polygon": [
                    {
                        "X": 0.2600739896297455,
                        "Y": 0.07870689779520035
                    },
                    {
                        "X": 0.2654893696308136,
                        "Y": 0.07871711999177933
                    },
                    {
                        "X": 0.26554155349731445,
                        "Y": 0.13727281987667084
                    },
                    {
                        "X": 0.26012617349624634,
                        "Y": 0.13726255297660828
                    }
                ]
            },
            "Id": "738f4e1e-46fd-416e-a52a-e4fc277292a7",
            "Text": ":",
            "TextType": "PRINTED"
        },
        {
            "BlockType": "WORD",
            "Confidence": 99.2329330444336,
            "Geometry": {
                "BoundingBox": {
                    "Height": 0.04473200440406799,
                    "Left": 0.2773037552833557,
                    "Top": 0.09593695402145386,
                    "Width": 0.017530526965856552
                },
                "Polygon": [
                    {
                        "X": 0.2773037552833557,
                        "Y": 0.09593695402145386
                    },
                    {
                        "X": 0.2947944402694702,
                        "Y": 0.09597001224756241
                    },
                    {
                        "X": 0.29483428597450256,
                        "Y": 0.14066895842552185
                    },
                    {
                        "X": 0.27734360098838806,
                        "Y": 0.14063578844070435
                    }
                ]
            },
            "Id": "9d91cc3a-92d3-440f-b434-80f08430225e",
            "Text": "20",
            "TextType": "PRINTED"
        },
        {
            "BlockType": "WORD",
            "Confidence": 99.79886627197266,
            "Geometry": {
                "BoundingBox": {
                    "Height": 0.044722624123096466,
                    "Left": 0.37313947081565857,
                    "Top": 0.09573612362146378,
                    "Width": 0.012852083891630173
                },
                "Polygon": [
                    {
                        "X": 0.37313947081565857,
                        "Y": 0.09573612362146378
                    },
                    {
                        "X": 0.3859516978263855,
                        "Y": 0.09576033800840378
                    },
                    {
                        "X": 0.38599157333374023,
                        "Y": 0.14045874774456024
                    },
                    {
                        "X": 0.3731793463230133,
                        "Y": 0.14043444395065308
                    }
                ]
            },
            "Id": "2ad020c6-8277-479b-aec6-f91b3383085a",
            "Text": "N",
            "TextType": "PRINTED"
        },
        {
            "BlockType": "WORD",
            "Confidence": 99.90121459960938,
            "Geometry": {
                "BoundingBox": {
                    "Height": 0.045112136751413345,
                    "Left": 0.43905943632125854,
                    "Top": 0.09625899791717529,
                    "Width": 0.042877599596977234
                },
                "Polygon": [
                    {
                        "X": 0.43905943632125854,
                        "Y": 0.09625899791717529
                    },
                    {
                        "X": 0.48189684748649597,
                        "Y": 0.09633995592594147
                    },
                    {
                        "X": 0.4819370210170746,
                        "Y": 0.14137113094329834
                    },
                    {
                        "X": 0.43909958004951477,
                        "Y": 0.14128988981246948
                    }
                ]
            },
            "Id": "7e90ef42-519e-4420-b8e4-40108c824fed",
            "Text": "90834",
            "TextType": "PRINTED"
        },
        {
            "BlockType": "WORD",
            "Confidence": 99.63639831542969,
            "Geometry": {
                "BoundingBox": {
                    "Height": 0.045983269810676575,
                    "Left": 0.5309964418411255,
                    "Top": 0.09516692906618118,
                    "Width": 0.021088890731334686
                },
                "Polygon": [
                    {
                        "X": 0.5309964418411255,
                        "Y": 0.09516692906618118
                    },
                    {
                        "X": 0.5520443916320801,
                        "Y": 0.09520670771598816
                    },
                    {
                        "X": 0.5520853400230408,
                        "Y": 0.14115020632743835
                    },
                    {
                        "X": 0.531037449836731,
                        "Y": 0.14111028611660004
                    }
                ]
            },
            "Id": "1a9b1e63-6834-402e-b160-03bd0ca99701",
            "Text": "U6",
            "TextType": "PRINTED"
        },
        {
            "BlockType": "WORD",
            "Confidence": 99.92787170410156,
            "Geometry": {
                "BoundingBox": {
                    "Height": 0.046367958188056946,
                    "Left": 0.8567051291465759,
                    "Top": 0.0946974903345108,
                    "Width": 0.017559316009283066
                },
                "Polygon": [
                    {
                        "X": 0.8567051291465759,
                        "Y": 0.0946974903345108
                    },
                    {
                        "X": 0.8742230534553528,
                        "Y": 0.09473059326410294
                    },
                    {
                        "X": 0.8742644190788269,
                        "Y": 0.14106544852256775
                    },
                    {
                        "X": 0.85674649477005,
                        "Y": 0.14103223383426666
                    }
                ]
            },
            "Id": "edb0844f-66f5-4422-bd36-aa97e24b27d1",
            "Text": "69",
            "TextType": "PRINTED"
        },
        {
            "BlockType": "WORD",
            "Confidence": 89.24274444580078,
            "Geometry": {
                "BoundingBox": {
                    "Height": 0.0574139766395092,
                    "Left": 0.8800302743911743,
                    "Top": 0.07945861667394638,
                    "Width": 0.005935013759881258
                },
                "Polygon": [
                    {
                        "X": 0.8800302743911743,
                        "Y": 0.07945861667394638
                    },
                    {
                        "X": 0.8859140276908875,
                        "Y": 0.0794697180390358
                    },
                    {
                        "X": 0.8859652876853943,
                        "Y": 0.13687258958816528
                    },
                    {
                        "X": 0.8800815343856812,
                        "Y": 0.13686144351959229
                    }
                ]
            },
            "Id": "2415d33e-afe1-4ea2-a774-beac1001dece",
            "Text": ":",
            "TextType": "PRINTED"
        },
        {
            "BlockType": "WORD",
            "Confidence": 99.85006713867188,
            "Geometry": {
                "BoundingBox": {
                    "Height": 0.04500124230980873,
                    "Left": 0.8979013562202454,
                    "Top": 0.09533959627151489,
                    "Width": 0.017771238461136818
                },
                "Polygon": [
                    {
                        "X": 0.8979013562202454,
                        "Y": 0.09533959627151489
                    },
                    {
                        "X": 0.915632426738739,
                        "Y": 0.09537310153245926
                    },
                    {
                        "X": 0.9156725406646729,
                        "Y": 0.14034083485603333
                    },
                    {
                        "X": 0.8979414701461792,
                        "Y": 0.1403072029352188
                    }
                ]
            },
            "Id": "e06d501a-a8ef-4079-a639-5edb87048f34",
            "Text": "74",
            "TextType": "PRINTED"
        },
        {
            "BlockType": "WORD",
            "Confidence": 97.15982818603516,
            "Geometry": {
                "BoundingBox": {
                    "Height": 0.04500617831945419,
                    "Left": 0.9329209327697754,
                    "Top": 0.09589587152004242,
                    "Width": 0.028548410162329674
                },
                "Polygon": [
                    {
                        "X": 0.9329209327697754,
                        "Y": 0.09589587152004242
                    },
                    {
                        "X": 0.9614291787147522,
                        "Y": 0.09594974666833878
                    },
                    {
                        "X": 0.9614693522453308,
                        "Y": 0.1409020572900772
                    },
                    {
                        "X": 0.9329610466957092,
                        "Y": 0.14084798097610474
                    }
                ]
            },
            "Id": "7c5296dd-40eb-47f1-97bc-0c131f0a98d2",
            "Text": "1.00",
            "TextType": "PRINTED"
        },
        {
            "BlockType": "WORD",
            "Confidence": 99.79341888427734,
            "Geometry": {
                "BoundingBox": {
                    "Height": 0.05610784888267517,
                    "Left": 0.02595418319106102,
                    "Top": 0.2168072909116745,
                    "Width": 0.011259674094617367
                },
                "Polygon": [
                    {
                        "X": 0.02595418319106102,
                        "Y": 0.2168072909116745
                    },
                    {
                        "X": 0.03716389462351799,
                        "Y": 0.21682867407798767
                    },
                    {
                        "X": 0.03721385821700096,
                        "Y": 0.27291515469551086
                    },
                    {
                        "X": 0.026004144921898842,
                        "Y": 0.27289366722106934
                    }
                ]
            },
            "Id": "10c201b5-eb7b-453f-a671-4b4b1fb9e5a5",
            "Text": "2",
            "TextType": "PRINTED"
        },
        {
            "BlockType": "WORD",
            "Confidence": 99.85658264160156,
            "Geometry": {
                "BoundingBox": {
                    "Height": 0.04529564455151558,
                    "Left": 0.05626837909221649,
                    "Top": 0.2657124102115631,
                    "Width": 0.015989314764738083
                },
                "Polygon": [
                    {
                        "X": 0.05626837909221649,
                        "Y": 0.2657124102115631
                    },
                    {
                        "X": 0.07221736758947372,
                        "Y": 0.2657429575920105
                    },
                    {
                        "X": 0.07225769013166428,
                        "Y": 0.3110080659389496
                    },
                    {
                        "X": 0.05630870535969734,
                        "Y": 0.31097739934921265
                    }
                ]
            },
            "Id": "e4a99ceb-8907-4366-ac97-4a7a045ada7c",
            "Text": "12",
            "TextType": "PRINTED"
        },
        {
            "BlockType": "WORD",
            "Confidence": 99.95601654052734,
            "Geometry": {
                "BoundingBox": {
                    "Height": 0.04562271013855934,
                    "Left": 0.09267235547304153,
                    "Top": 0.26535433530807495,
                    "Width": 0.017770078033208847
                },
                "Polygon": [
                    {
                        "X": 0.09267235547304153,
                        "Y": 0.26535433530807495
                    },
                    {
                        "X": 0.11040181666612625,
                        "Y": 0.26538828015327454
                    },
                    {
                        "X": 0.11044243723154068,
                        "Y": 0.310977041721344
                    },
                    {
                        "X": 0.09271297603845596,
                        "Y": 0.31094297766685486
                    }
                ]
            },
            "Id": "f9895571-9d24-4417-a46c-5070cc78f516",
            "Text": "09",
            "TextType": "PRINTED"
        },
        {
            "BlockType": "WORD",
            "Confidence": 99.89064025878906,
            "Geometry": {
                "BoundingBox": {
                    "Height": 0.045544568449258804,
                    "Left": 0.1385493129491806,
                    "Top": 0.26516157388687134,
                    "Width": 0.017374582588672638
                },
                "Polygon": [
                    {
                        "X": 0.1385493129491806,
                        "Y": 0.26516157388687134
                    },
                    {
                        "X": 0.15588334202766418,
                        "Y": 0.26519477367401123
                    },
                    {
                        "X": 0.15592388808727264,
                        "Y": 0.31070616841316223
                    },
                    {
                        "X": 0.13858987390995026,
                        "Y": 0.3106728494167328
                    }
                ]
            },
            "Id": "dc4cd42e-6475-42d2-a1a8-b2bc68eb9476",
            "Text": "20",
            "TextType": "PRINTED"
        },
        {
            "BlockType": "WORD",
            "Confidence": 99.69669342041016,
            "Geometry": {
                "BoundingBox": {
                    "Height": 0.045257873833179474,
                    "Left": 0.18564236164093018,
                    "Top": 0.2654660642147064,
                    "Width": 0.01642664708197117
                },
                "Polygon": [
                    {
                        "X": 0.18564236164093018,
                        "Y": 0.2654660642147064
                    },
                    {
                        "X": 0.20202870666980743,
                        "Y": 0.26549744606018066
                    },
                    {
                        "X": 0.2020690143108368,
                        "Y": 0.3107239603996277
                    },
                    {
                        "X": 0.18568266928195953,
                        "Y": 0.3106924593448639
                    }
                ]
            },
            "Id": "42ca010b-225e-484e-aa1e-cde0a53526b5",
            "Text": "12",
            "TextType": "PRINTED"
        },
        {
            "BlockType": "WORD",
            "Confidence": 99.3494873046875,
            "Geometry": {
                "BoundingBox": {
                    "Height": 0.04485385864973068,
                    "Left": 0.22903896868228912,
                    "Top": 0.2658660411834717,
                    "Width": 0.018566258251667023
                },
                "Polygon": [
                    {
                        "X": 0.22903896868228912,
                        "Y": 0.2658660411834717
                    },
                    {
                        "X": 0.24756528437137604,
                        "Y": 0.26590150594711304
                    },
                    {
                        "X": 0.24760523438453674,
                        "Y": 0.31071987748146057
                    },
                    {
                        "X": 0.22907891869544983,
                        "Y": 0.31068429350852966
                    }
                ]
            },
            "Id": "c385671c-0a1c-432d-a98c-f9be02b065df",
            "Text": "09",
            "TextType": "PRINTED"
        },
        {
            "BlockType": "WORD",
            "Confidence": 99.02058410644531,
            "Geometry": {
                "BoundingBox": {
                    "Height": 0.04509974271059036,
                    "Left": 0.2769503891468048,
                    "Top": 0.2657829523086548,
                    "Width": 0.01728205941617489
                },
                "Polygon": [
                    {
                        "X": 0.2769503891468048,
                        "Y": 0.2657829523086548
                    },
                    {
                        "X": 0.29419228434562683,
                        "Y": 0.26581597328186035
                    },
                    {
                        "X": 0.29423245787620544,
                        "Y": 0.31088268756866455
                    },
                    {
                        "X": 0.2769905626773834,
                        "Y": 0.31084954738616943
                    }
                ]
            },
            "Id": "3b0b992a-6c44-4923-9eb6-7d1c2ebfe8d0",
            "Text": "20",
            "TextType": "PRINTED"
        },
        {
            "BlockType": "WORD",
            "Confidence": 93.3573989868164,
            "Geometry": {
                "BoundingBox": {
                    "Height": 0.044209521263837814,
                    "Left": 0.3242138624191284,
                    "Top": 0.26611897349357605,
                    "Width": 0.014980372041463852
                },
                "Polygon": [
                    {
                        "X": 0.3242138624191284,
                        "Y": 0.26611897349357605
                    },
                    {
                        "X": 0.33915483951568604,
                        "Y": 0.26614758372306824
                    },
                    {
                        "X": 0.33919423818588257,
                        "Y": 0.31032848358154297
                    },
                    {
                        "X": 0.32425326108932495,
                        "Y": 0.3102997839450836
                    }
                ]
            },
            "Id": "88c9a6ba-4ec2-4cd7-ab66-2ce7eca37fa8",
            "Text": "11",
            "TextType": "PRINTED"
        },
        {
            "BlockType": "WORD",
            "Confidence": 99.90327453613281,
            "Geometry": {
                "BoundingBox": {
                    "Height": 0.045588213950395584,
                    "Left": 0.3731483221054077,
                    "Top": 0.26455411314964294,
                    "Width": 0.012919125147163868
                },
                "Polygon": [
                    {
                        "X": 0.3731483221054077,
                        "Y": 0.26455411314964294
                    },
                    {
                        "X": 0.3860268294811249,
                        "Y": 0.26457878947257996
                    },
                    {
                        "X": 0.3860674500465393,
                        "Y": 0.3101423382759094
                    },
                    {
                        "X": 0.37318894267082214,
                        "Y": 0.31011760234832764
                    }
                ]
            },
            "Id": "76bb1556-e1ba-4e5d-a9f9-94902a065326",
            "Text": "N",
            "TextType": "PRINTED"
        },
        {
            "BlockType": "WORD",
            "Confidence": 88.85499572753906,
            "Geometry": {
                "BoundingBox": {
                    "Height": 0.047276221215724945,
                    "Left": 0.4362429678440094,
                    "Top": 0.2644710838794708,
                    "Width": 0.04769366979598999
                },
                "Polygon": [
                    {
                        "X": 0.4362429678440094,
                        "Y": 0.2644710838794708
                    },
                    {
                        "X": 0.48389455676078796,
                        "Y": 0.26456233859062195
                    },
                    {
                        "X": 0.4839366376399994,
                        "Y": 0.31174731254577637
                    },
                    {
                        "X": 0.4362850487232208,
                        "Y": 0.311655730009079
                    }
                ]
            },
            "Id": "d1099fb1-fbee-42fa-9090-8a9c5fa162b8",
            "Text": "110048",
            "TextType": "PRINTED"
        },
        {
            "BlockType": "WORD",
            "Confidence": 90.33728790283203,
            "Geometry": {
                "BoundingBox": {
                    "Height": 0.047508589923381805,
                    "Left": 0.7154537439346313,
                    "Top": 0.2642938196659088,
                    "Width": 0.007012603338807821
                },
                "Polygon": [
                    {
                        "X": 0.7154537439346313,
                        "Y": 0.2642938196659088
                    },
                    {
                        "X": 0.7224239706993103,
                        "Y": 0.2643071711063385
                    },
                    {
                        "X": 0.7224663496017456,
                        "Y": 0.3118024170398712
                    },
                    {
                        "X": 0.7154961228370667,
                        "Y": 0.31178900599479675
                    }
                ]
            },
            "Id": "6d9386ca-c1d1-462e-b87c-8a5d8e5a095d",
            "Text": "1",
            "TextType": "PRINTED"
        },
        {
            "BlockType": "WORD",
            "Confidence": 99.91776275634766,
            "Geometry": {
                "BoundingBox": {
                    "Height": 0.04535893723368645,
                    "Left": 0.8582285046577454,
                    "Top": 0.2653377652168274,
                    "Width": 0.016538573428988457
                },
                "Polygon": [
                    {
                        "X": 0.8582285046577454,
                        "Y": 0.2653377652168274
                    },
                    {
                        "X": 0.8747265934944153,
                        "Y": 0.26536935567855835
                    },
                    {
                        "X": 0.8747670650482178,
                        "Y": 0.31069669127464294
                    },
                    {
                        "X": 0.8582689762115479,
                        "Y": 0.3106650114059448
                    }
                ]
            },
            "Id": "b33b1831-d3ff-43b7-9c47-9cb1a558f87e",
            "Text": "14",
            "TextType": "PRINTED"
        },
        {
            "BlockType": "WORD",
            "Confidence": 99.79928588867188,
            "Geometry": {
                "BoundingBox": {
                    "Height": 0.04683927819132805,
                    "Left": 0.8980045318603516,
                    "Top": 0.2645419239997864,
                    "Width": 0.017436541616916656
                },
                "Polygon": [
                    {
                        "X": 0.8980045318603516,
                        "Y": 0.2645419239997864
                    },
                    {
                        "X": 0.9153993129730225,
                        "Y": 0.2645752429962158
                    },
                    {
                        "X": 0.91544109582901,
                        "Y": 0.31138119101524353
                    },
                    {
                        "X": 0.8980463147163391,
                        "Y": 0.3113477826118469
                    }
                ]
            },
            "Id": "de93b898-7960-4a35-9348-f475c0b02e20",
            "Text": "48",
            "TextType": "PRINTED"
        },
        {
            "BlockType": "WORD",
            "Confidence": 99.82959747314453,
            "Geometry": {
                "BoundingBox": {
                    "Height": 0.04632692039012909,
                    "Left": 0.932571291923523,
                    "Top": 0.26500779390335083,
                    "Width": 0.028995519503951073
                },
                "Polygon": [
                    {
                        "X": 0.932571291923523,
                        "Y": 0.26500779390335083
                    },
                    {
                        "X": 0.9615254998207092,
                        "Y": 0.26506322622299194
                    },
                    {
                        "X": 0.9615668654441833,
                        "Y": 0.3113346993923187
                    },
                    {
                        "X": 0.9326126575469971,
                        "Y": 0.3112790584564209
                    }
                ]
            },
            "Id": "7c62a70f-a3e4-4a65-92c8-7e86e1042545",
            "Text": "1.00",
            "TextType": "PRINTED"
        },
        {
            "BlockType": "WORD",
            "Confidence": 99.4665756225586,
            "Geometry": {
                "BoundingBox": {
                    "Height": 0.06432473659515381,
                    "Left": 0.02487802878022194,
                    "Top": 0.3840811848640442,
                    "Width": 0.011113501153886318
                },
                "Polygon": [
                    {
                        "X": 0.02487802878022194,
                        "Y": 0.3840811848640442
                    },
                    {
                        "X": 0.03593424707651138,
                        "Y": 0.38410255312919617
                    },
                    {
                        "X": 0.03599153086543083,
                        "Y": 0.448405921459198
                    },
                    {
                        "X": 0.02493531070649624,
                        "Y": 0.44838446378707886
                    }
                ]
            },
            "Id": "95e4d7fc-056c-42ac-abda-f00dcf1023f0",
            "Text": "3",
            "TextType": "PRINTED"
        },
        {
            "BlockType": "WORD",
            "Confidence": 99.91659545898438,
            "Geometry": {
                "BoundingBox": {
                    "Height": 0.056307971477508545,
                    "Left": 0.026298193261027336,
                    "Top": 0.5553244352340698,
                    "Width": 0.011234186589717865
                },
                "Polygon": [
                    {
                        "X": 0.026298193261027336,
                        "Y": 0.5553244352340698
                    },
                    {
                        "X": 0.03748223930597305,
                        "Y": 0.5553463101387024
                    },
                    {
                        "X": 0.03753238171339035,
                        "Y": 0.6116324067115784
                    },
                    {
                        "X": 0.026348333805799484,
                        "Y": 0.6116104125976562
                    }
                ]
            },
            "Id": "8b27c573-f4f5-4ece-8e2f-01124d6262d3",
            "Text": "4",
            "TextType": "PRINTED"
        },
        {
            "BlockType": "WORD",
            "Confidence": 99.08972930908203,
            "Geometry": {
                "BoundingBox": {
                    "Height": 0.05685964971780777,
                    "Left": 0.026742946356534958,
                    "Top": 0.7319079637527466,
                    "Width": 0.010450838133692741
                },
                "Polygon": [
                    {
                        "X": 0.026742946356534958,
                        "Y": 0.7319079637527466
                    },
                    {
                        "X": 0.037143148481845856,
                        "Y": 0.7319285869598389
                    },
                    {
                        "X": 0.03719378262758255,
                        "Y": 0.7887676358222961
                    },
                    {
                        "X": 0.026793578639626503,
                        "Y": 0.7887468934059143
                    }
                ]
            },
            "Id": "3518a893-2198-44e0-8561-6964f3695b34",
            "Text": "5",
            "TextType": "PRINTED"
        },
        {
            "BlockType": "WORD",
            "Confidence": 99.87584686279297,
            "Geometry": {
                "BoundingBox": {
                    "Height": 0.05692388117313385,
                    "Left": 0.026133118197321892,
                    "Top": 0.9041671752929688,
                    "Width": 0.011987566947937012
                },
                "Polygon": [
                    {
                        "X": 0.026133118197321892,
                        "Y": 0.9041671752929688
                    },
                    {
                        "X": 0.03806999698281288,
                        "Y": 0.9041911363601685
                    },
                    {
                        "X": 0.038120683282613754,
                        "Y": 0.9610910415649414
                    },
                    {
                        "X": 0.026183804497122765,
                        "Y": 0.9610669612884521
                    }
                ]
            },
            "Id": "635a593f-c70f-4e0b-a888-51ad8f20aade",
            "Text": "6",
            "TextType": "PRINTED"
        }
    ],
    "Pages": 71
}